open_mcp/__init__.py
open_mcp/__main__.py
open_mcp/mcp_server_ypt.py
azt_mcp_server-0.1.4.dist-info/METADATA
azt_mcp_server-0.1.4.dist-info/WHEEL
azt_mcp_server-0.1.4.dist-info/entry_points.txt
azt_mcp_server-0.1.4.dist-info/top_level.txt
azt_mcp_server-0.1.4.dist-info/RECORD
