Metadata-Version: 2.4
Name: azt-mcp-server
Version: 0.1.4
Summary: Add your description here
Requires-Python: >=3.12
Requires-Dist: build>=1.2.2.post1
Requires-Dist: httpx>=0.28.1
Requires-Dist: mcp[cli]>=1.10.1
Requires-Dist: requests>=2.32.4
Requires-Dist: twine>=6.1.0
